analyses/causality_test.py
analyses/cbf_lrb_regr_ts.py
analyses/conditioned_regressions.py
analyses/density_estimation.py
analyses/lrb_acceptable_design.py
analyses/mixed_figures.py
analyses/non_impact_data.py
analyses/per_system_inverse_design.py
analyses/run_a_design.py
analyses/sample_inverse_design.py
analyses/sensitivity_anly_sys.py
analyses/significance_testing.py
analyses/system_classification.py
analyses/system_selection.py
analyses/upfront_cost.py
archive/design_superstructure.py
archive/frame.py
archive/main.py
archive/old_bearing_designs.py
archive/scale_ground_motion.py
archive/shear_wall_design.py
bearings/__init__.py
paper/emi_figures.py
paper/eng_struc_loss_figures.py
paper/paper_figures.py
paper/paper_review_figures.py
paper/sensitivity_analysis.py
bearings-0.0.0.dist-info/LICENSE
bearings-0.0.0.dist-info/METADATA
bearings-0.0.0.dist-info/WHEEL
bearings-0.0.0.dist-info/top_level.txt
bearings-0.0.0.dist-info/RECORD
