Metadata-Version: 2.1
Name: bearings
Version: 0.0.0
Author-email: "Huy G. Pham" <62033779+hgp297@users.noreply.github.com>
Project-URL: Repository, http://github.com/hgp297/isol-sys-database
Keywords: seismic,earthquake
License-File: LICENSE
